tap_sdk_py-1.0.2.dist-info/licenses/LICENSE
zakotap/__init__.py
zakotap/client.py
zakotap/utils/__init__.py
zakotap/utils/_type.py
zakotap/utils/event.py
zakotap/utils/response.py
zakotap/utils/websocket.py
tap_sdk_py-1.0.2.dist-info/METADATA
tap_sdk_py-1.0.2.dist-info/WHEEL
tap_sdk_py-1.0.2.dist-info/top_level.txt
tap_sdk_py-1.0.2.dist-info/RECORD
