Metadata-Version: 2.4
Name: tap-sdk-py
Version: 1.0.2
Summary: Zako tap server sdk for python
Home-page: https://github.com/zako-ac/tap-sdk-py
Author: ridanit_ruma
Author-email: me@inizeno.com
License: MIT License
Classifier: Development Status :: 5 - Production/Stable
Classifier: Intended Audience :: Developers
Classifier: License :: OSI Approved :: MIT License
Classifier: Programming Language :: Python :: 3.11
Requires-Python: >=3.11
License-File: LICENSE
Requires-Dist: eventemitter>=0.2.0
Requires-Dist: requests>=2.32.4
Requires-Dist: websockets>=15.0.1
Dynamic: author
Dynamic: author-email
Dynamic: home-page
Dynamic: license-file
